LICENSE.txt
MANIFEST.in
README.rst
setup.py
51degrees_mobile_detector_v3_wrapper.egg-info/PKG-INFO
51degrees_mobile_detector_v3_wrapper.egg-info/SOURCES.txt
51degrees_mobile_detector_v3_wrapper.egg-info/dependency_links.txt
51degrees_mobile_detector_v3_wrapper.egg-info/requires.txt
51degrees_mobile_detector_v3_wrapper.egg-info/top_level.txt
FiftyOneDegrees/__init__.py
FiftyOneDegrees/fiftyone_degrees_mobile_detector_v3_wrapper.py
data/51Degrees-LiteV3.2.dat
src/threading.c
src/threading.h
src/cityhash/LICENSE
src/cityhash/city.c
src/cityhash/city.h
src/pattern/51Degrees.c
src/pattern/51Degrees.h
src/pattern/51Degrees.i
src/pattern/51Degrees_PHP.cpp
src/pattern/51Degrees_csharp.cxx
src/pattern/51Degrees_go.cxx
src/pattern/51Degrees_lua.cpp
src/pattern/51Degrees_node.cpp
src/pattern/51Degrees_perl.cxx
src/pattern/51Degrees_python.cxx
src/pattern/FiftyOneDegreesPatternV3.go
src/pattern/Match.cpp
src/pattern/Match.hpp
src/pattern/PerfPat.c
src/pattern/ProcPat.c
src/pattern/Profiles.cpp
src/pattern/Profiles.hpp
src/pattern/Provider.cpp
src/pattern/Provider.hpp
src/pattern/php_FiftyOneDegreesPatternV3.h